{
  "lat": 50.0606,
  "lon": 19.9371,
  "timezone": "Europe/Warsaw",
  "timezone_offset": 7200,
  "current": {
    "dt": 1680029389,
    "sunrise": 1679977592,
    "sunset": 1680023049,
    "temp": -0.07,
    "feels_like": -4.45,
    "pressure": 1022,
    "humidity": 71,
    "dew_point": -4.16,
    "uvi": 0,
    "clouds": 75,
    "visibility": 10000,
    "wind_speed": 4.12,
    "wind_deg": 300,
    "weather": [
      {
        "id": 803,
        "main": "Clouds",
        "description": "broken clouds",
        "icon": "04n"
      }
    ]
  },
  "daily": [
    {
      "dt": 1679997600,
      "sunrise": 1679977592,
      "sunset": 1680023049,
      "moonrise": 1679989080,
      "moonset": 1679963280,
      "moon_phase": 0.23,
      "temp": {
        "day": 3.19,
        "min": -1.28,
        "max": 3.94,
        "night": -0.4,
        "eve": 0.54,
        "morn": -1.03
      },
      "feels_like": {
        "day": -2.66,
        "night": -5.43,
        "eve": -5.48,
        "morn": -6.78
      },
      "pressure": 1016,
      "humidity": 47,
      "dew_point": -7.22,
      "wind_speed": 9.49,
      "wind_deg": 320,
      "wind_gust": 12.57,
      "weather": [
        {
          "id": 600,
          "main": "Snow",
          "description": "light snow",
          "icon": "13d"
        }
      ],
      "clouds": 98,
      "pop": 0.99,
      "snow": 1.61,
      "uvi": 2.35
    },
    {
      "dt": 1680084000,
      "sunrise": 1680063861,
      "sunset": 1680109543,
      "moonrise": 1680078540,
      "moonset": 1680053100,
      "moon_phase": 0.25,
      "temp": {
        "day": 5.13,
        "min": -2.4,
        "max": 7.79,
        "night": 1.77,
        "eve": 6.45,
        "morn": -2.4
      },
      "feels_like": {
        "day": 2.03,
        "night": -0.39,
        "eve": 5.5,
        "morn": -6.34
      },
      "pressure": 1023,
      "humidity": 34,
      "dew_point": -9.66,
      "wind_speed": 4.15,
      "wind_deg": 295,
      "wind_gust": 9.16,
      "weather": [
        {
          "id": 803,
          "main": "Clouds",
          "description": "broken clouds",
          "icon": "04d"
        }
      ],
      "clouds": 80,
      "pop": 0,
      "uvi": 3.15
    },
    {
      "dt": 1680170400,
      "sunrise": 1680150129,
      "sunset": 1680196037,
      "moonrise": 1680168660,
      "moonset": 1680142140,
      "moon_phase": 0.29,
      "temp": {
        "day": 7.86,
        "min": 1.43,
        "max": 12.91,
        "night": 8.21,
        "eve": 11.25,
        "morn": 3.13
      },
      "feels_like": {
        "day": 6.48,
        "night": 6.89,
        "eve": 10.36,
        "morn": 1.12
      },
      "pressure": 1016,
      "humidity": 82,
      "dew_point": 4.7,
      "wind_speed": 5.4,
      "wind_deg": 244,
      "wind_gust": 8.91,
      "weather": [
        {
          "id": 500,
          "main": "Rain",
          "description": "light rain",
          "icon": "10d"
        }
      ],
      "clouds": 100,
      "pop": 0.56,
      "rain": 0.59,
      "uvi": 2.05
    },
    {
      "dt": 1680256800,
      "sunrise": 1680236398,
      "sunset": 1680282531,
      "moonrise": 1680259140,
      "moonset": 1680230520,
      "moon_phase": 0.32,
      "temp": {
        "day": 11.5,
        "min": 8,
        "max": 14.58,
        "night": 9.9,
        "eve": 13.39,
        "morn": 8.71
      },
      "feels_like": {
        "day": 10.66,
        "night": 9.9,
        "eve": 12.46,
        "morn": 6.22
      },
      "pressure": 1007,
      "humidity": 75,
      "dew_point": 6.94,
      "wind_speed": 5.04,
      "wind_deg": 255,
      "wind_gust": 12.42,
      "weather": [
        {
          "id": 500,
          "main": "Rain",
          "description": "light rain",
          "icon": "10d"
        }
      ],
      "clouds": 97,
      "pop": 1,
      "rain": 2.23,
      "uvi": 3.29
    },
    {
      "dt": 1680343200,
      "sunrise": 1680322667,
      "sunset": 1680369025,
      "moonrise": 1680349800,
      "moonset": 1680318480,
      "moon_phase": 0.35,
      "temp": {
        "day": 8.71,
        "min": 7.87,
        "max": 9.03,
        "night": 7.87,
        "eve": 8.75,
        "morn": 8.52
      },
      "feels_like": {
        "day": 6.29,
        "night": 5.85,
        "eve": 6.6,
        "morn": 7.49
      },
      "pressure": 1000,
      "humidity": 92,
      "dew_point": 7.17,
      "wind_speed": 4.32,
      "wind_deg": 266,
      "wind_gust": 7.9,
      "weather": [
        {
          "id": 501,
          "main": "Rain",
          "description": "moderate rain",
          "icon": "10d"
        }
      ],
      "clouds": 100,
      "pop": 0.95,
      "rain": 9.3,
      "uvi": 0.83
    },
    {
      "dt": 1680429600,
      "sunrise": 1680408936,
      "sunset": 1680455518,
      "moonrise": 1680440460,
      "moonset": 1680406020,
      "moon_phase": 0.38,
      "temp": {
        "day": 4.33,
        "min": 1.82,
        "max": 7.17,
        "night": 1.82,
        "eve": 2.98,
        "morn": 7.09
      },
      "feels_like": {
        "day": 0.77,
        "night": -2.26,
        "eve": 0.08,
        "morn": 4.35
      },
      "pressure": 1008,
      "humidity": 95,
      "dew_point": 3.29,
      "wind_speed": 4.48,
      "wind_deg": 13,
      "wind_gust": 8.49,
      "weather": [
        {
          "id": 616,
          "main": "Snow",
          "description": "rain and snow",
          "icon": "13d"
        }
      ],
      "clouds": 100,
      "pop": 0.94,
      "rain": 2.29,
      "snow": 3.78,
      "uvi": 0.45
    },
    {
      "dt": 1680516000,
      "sunrise": 1680495206,
      "sunset": 1680542012,
      "moonrise": 1680531120,
      "moonset": 1680493380,
      "moon_phase": 0.41,
      "temp": {
        "day": 1.71,
        "min": -0.36,
        "max": 2.43,
        "night": 0.61,
        "eve": 2.32,
        "morn": -0.36
      },
      "feels_like": {
        "day": -2.64,
        "night": -3.74,
        "eve": -1.89,
        "morn": -4.92
      },
      "pressure": 1021,
      "humidity": 75,
      "dew_point": -2.52,
      "wind_speed": 4.85,
      "wind_deg": 327,
      "wind_gust": 9.33,
      "weather": [
        {
          "id": 616,
          "main": "Snow",
          "description": "rain and snow",
          "icon": "13d"
        }
      ],
      "clouds": 100,
      "pop": 0.84,
      "rain": 0.11,
      "snow": 0.93,
      "uvi": 1
    },
    {
      "dt": 1680602400,
      "sunrise": 1680581476,
      "sunset": 1680628506,
      "moonrise": 1680621780,
      "moonset": 1680580560,
      "moon_phase": 0.44,
      "temp": {
        "day": -0.31,
        "min": -1.6,
        "max": 2.01,
        "night": -1.6,
        "eve": 2.01,
        "morn": -0.1
      },
      "feels_like": {
        "day": -6,
        "night": -6.93,
        "eve": -3.06,
        "morn": -5.31
      },
      "pressure": 1023,
      "humidity": 94,
      "dew_point": -1.46,
      "wind_speed": 7.05,
      "wind_deg": 34,
      "wind_gust": 12.32,
      "weather": [
        {
          "id": 600,
          "main": "Snow",
          "description": "light snow",
          "icon": "13d"
        }
      ],
      "clouds": 100,
      "pop": 0.92,
      "snow": 5.93,
      "uvi": 1
    }
  ]
}